asciicaptcha/__init__.py
asciicaptcha/__main__.py
asciicaptcha/fonts.py
ASCIICaptcha-1.0.2.dist-info/LICENSE
ASCIICaptcha-1.0.2.dist-info/METADATA
ASCIICaptcha-1.0.2.dist-info/WHEEL
ASCIICaptcha-1.0.2.dist-info/top_level.txt
ASCIICaptcha-1.0.2.dist-info/RECORD
