Metadata-Version: 2.1
Name: ASCIICaptcha
Version: 1.0.2
Summary: A Python Library to generate simple ASCII Captchas
Home-page: https://github.com/Defelo/ASCIICaptcha
Author: Defelo
Author-email: elodef42@gmail.com
License: UNKNOWN
Platform: UNKNOWN
Requires-Dist: pyfiglet (>=0.8.post1)
